streamui/__init__.py
streamui/filter_box.py
streamui-0.1.2.dist-info/METADATA
streamui-0.1.2.dist-info/WHEEL
streamui-0.1.2.dist-info/RECORD
