Metadata-Version: 2.1
Name: streamui
Version: 0.1.2
Summary: 
Author: Nate Smith
Author-email: nate@cloudcrestgroup.com
Requires-Python: >=3.9,<4.0
Classifier: Programming Language :: Python :: 3
Classifier: Programming Language :: Python :: 3.9
Classifier: Programming Language :: Python :: 3.10
Classifier: Programming Language :: Python :: 3.11
Classifier: Programming Language :: Python :: 3.12
Requires-Dist: altair[all] (>=5.3.0,<6.0.0)
Requires-Dist: ipywidgets (>=8.1.3,<9.0.0)
Requires-Dist: pandas (>=2.2.2,<3.0.0)
